spsdk_pylint_plugins/__init__.py
spsdk_pylint_plugins/assert_isinstance_checker.py
spsdk_pylint_plugins/click_choice_check.py
spsdk_pylint_plugins/typing_checker.py
spsdk_pylint_plugins-0.2.1.dist-info/LICENSE
spsdk_pylint_plugins-0.2.1.dist-info/METADATA
spsdk_pylint_plugins-0.2.1.dist-info/WHEEL
spsdk_pylint_plugins-0.2.1.dist-info/top_level.txt
spsdk_pylint_plugins-0.2.1.dist-info/RECORD
